decision_fetcher/__init__.py
decision_fetcher/__main__.py
decision_fetcher/config.py
decision_fetcher/dissect.py
decision_fetcher/draft.py
decision_fetcher/items.py
decision_fetcher/logger.py
decision_fetcher/sanitize.py
decision_fetcher_fields/__init__.py
decision_fetcher_fields/citation.py
decision_fetcher_fields/cullables.py
decision_fetcher_fields/footnotes.py
decision_fetcher_fields/header.py
decision_fetcher_fields/ruling.py
decision_fetcher_fields/ruling_cues.py
decision_fetcher_fields/title_tags.py
decision_fetcher_fields/utils.py
decision_fetcher_fields/voteline.py
decision_fetcher_fields/writer.py
decision_fetcher_fields/dispositive/__init__.py
decision_fetcher_fields/dispositive/ordered.py
decision_fetcher_fields/dispositive/phrases.py
decision_fetcher_fields/dispositive/wherefore.py
decision_fetcher_fields/ruling_patterns/__init__.py
decision_fetcher_fields/ruling_patterns/after_review.py
decision_fetcher_fields/ruling_patterns/court_acts.py
decision_fetcher_fields/ruling_patterns/court_admin.py
decision_fetcher_fields/ruling_patterns/granted_denied.py
decision_fetcher_fields/ruling_patterns/hence_this.py
decision_fetcher_fields/ruling_patterns/issue_errors.py
decision_fetcher_fields/ruling_patterns/issue_resolution.py
decision_fetcher_fields/ruling_patterns/main_issue.py
decision_fetcher_fields/ruling_patterns/merit.py
decision_fetcher_fields/ruling_patterns/resolve_issue.py
decision_fetcher_fields/ruling_patterns/single_issue.py
decision_fetcher_fields/tags/__init__.py
decision_fetcher_fields/tags/base.py
decision_fetcher_fields/tags/specific.py
decision_fetcher_fields/tags/utils.py
decision_updater/__init__.py
decision_updater/__main__.py
decision_updater/clean.py
decision_updater/dumper.py
decision_updater/logger.py
decision_updater/md.py
decision_updater/writer.py
decision_utils/__init__.py
decision_utils/__main__.py
decision_utils/author.py
decision_utils/block.py
decision_utils/decision.py
decision_utils/opinion.py
decision_utils-0.0.11.dist-info/METADATA
decision_utils-0.0.11.dist-info/WHEEL
decision_utils-0.0.11.dist-info/entry_points.txt
decision_utils-0.0.11.dist-info/top_level.txt
decision_utils-0.0.11.dist-info/RECORD
