Metadata-Version: 2.1
Name: decision-utils
Version: 0.0.11
Summary: Preprocess frontmatter-ish markdown with Philippine artifacts, statutes, citations.
Requires-Python: >=3.11
Requires-Dist: statute-utils >=0.6.15
Requires-Dist: citation-utils >=0.4.13
Requires-Dist: citation-title >=0.0.1
Requires-Dist: corpus-judge >=0.1.6
Requires-Dist: environs >=11.0
Requires-Dist: markdownify >=0.13.1
Requires-Dist: httpx >=0.27.0
Requires-Dist: html-sanitizer >=2.4.4
Requires-Dist: beautifulsoup4 >=4.12.3
Requires-Dist: watchdog >=4.0
Requires-Dist: python-frontmatter >=1.1.0
Requires-Dist: rich >=13.7
Provides-Extra: dev
Requires-Dist: ipykernel >=6.29 ; extra == 'dev'
Requires-Dist: pytest >=8.3 ; extra == 'dev'
Requires-Dist: pytest-cov >=5.0 ; extra == 'dev'
Requires-Dist: mkdocs >=1.6.0 ; extra == 'dev'
Requires-Dist: mkdocstrings[python] >=0.25.1 ; extra == 'dev'
Requires-Dist: mkdocs-material >=9.5 ; extra == 'dev'
Requires-Dist: build >=1.2.1 ; extra == 'dev'
Requires-Dist: twine >=5.1.1 ; extra == 'dev'
